GeneralBacktest/__init__.py
GeneralBacktest/backtest.py
GeneralBacktest/utils.py
generalbacktest-1.0.2.dist-info/licenses/LICENSE
generalbacktest-1.0.2.dist-info/METADATA
generalbacktest-1.0.2.dist-info/WHEEL
generalbacktest-1.0.2.dist-info/top_level.txt
generalbacktest-1.0.2.dist-info/RECORD
