Metadata-Version: 2.4
Name: GeneralBacktest
Version: 1.0.2
Summary: 一个灵活高效的量化策略回测框架，支持多资产组合、任意调仓频率、向量化计算和丰富的性能分析
Author-email: Elen Young <yang13515360252@163.com>
License: MIT
Project-URL: Homepage, https://github.com/ElenYoung/GeneralBacktest
Project-URL: Bug Reports, https://github.com/ElenYoung/GeneralBacktest/issues
Project-URL: Source, https://github.com/ElenYoung/GeneralBacktest
Project-URL: Documentation, https://github.com/ElenYoung/GeneralBacktest#readme
Keywords: backtest,quantitative,trading,finance,portfolio
Classifier: Development Status :: 4 - Beta
Classifier: Intended Audience :: Financial and Insurance Industry
Classifier: Intended Audience :: Science/Research
Classifier: License :: OSI Approved :: MIT License
Classifier: Programming Language :: Python :: 3
Classifier: Programming Language :: Python :: 3.8
Classifier: Programming Language :: Python :: 3.9
Classifier: Programming Language :: Python :: 3.10
Classifier: Programming Language :: Python :: 3.11
Classifier: Programming Language :: Python :: 3.12
Classifier: Programming Language :: Python :: 3.13
Classifier: Topic :: Office/Business :: Financial :: Investment
Classifier: Topic :: Scientific/Engineering
Requires-Python: >=3.8
License-File: LICENSE
Requires-Dist: numpy>=1.20.0
Requires-Dist: pandas>=1.3.0
Requires-Dist: matplotlib>=3.3.0
Provides-Extra: database
Requires-Dist: quantchdb>=0.1.0; extra == "database"
Provides-Extra: excel
Requires-Dist: openpyxl>=3.0.0; extra == "excel"
Provides-Extra: full
Requires-Dist: quantchdb>=0.1.0; extra == "full"
Requires-Dist: openpyxl>=3.0.0; extra == "full"
Dynamic: license-file
